bananadm-1.12.8.data/scripts/bananadm
libbananadm/__init__.py
libbananadm/agent.py
libbananadm/args.py
libbananadm/backend.py
libbananadm/client.py
libbananadm/input.py
libbananadm/monitor.py
libbananadm/policies.py
libbananadm/user.py
libbananadm/vault.py
bananadm-1.12.8.dist-info/METADATA
bananadm-1.12.8.dist-info/WHEEL
bananadm-1.12.8.dist-info/top_level.txt
bananadm-1.12.8.dist-info/RECORD
